Arbie/__init__.py
Arbie/__main__.py
Arbie/address.py
Arbie/app.py
Arbie/async_helpers.py
Arbie/exception.py
Arbie/prometheus.py
Arbie/settings_parser.py
Arbie/Actions/__init__.py
Arbie/Actions/action.py
Arbie/Actions/action_tree.py
Arbie/Actions/arbitrage.py
Arbie/Actions/path_finder.py
Arbie/Actions/pool_finder.py
Arbie/Actions/pool_updater.py
Arbie/Actions/redis_state.py
Arbie/Actions/trader.py
Arbie/Actions/whitelist.py
Arbie/Contracts/__init__.py
Arbie/Contracts/balancer.py
Arbie/Contracts/contract.py
Arbie/Contracts/event_filter.py
Arbie/Contracts/pool_contract.py
Arbie/Contracts/tokens.py
Arbie/Contracts/uniswap.py
Arbie/Contracts/uniswap_router.py
Arbie/Services/__init__.py
Arbie/Services/coingecko.py
Arbie/Store/__init__.py
Arbie/Variables/__init__.py
Arbie/Variables/big_number.py
Arbie/Variables/graph.py
Arbie/Variables/pool.py
Arbie/Variables/token.py
Arbie/Variables/trades.py
Arbie/resources/__init__.py
Arbie/resources/contracts/__init__.py
Arbie/resources/contracts/contract_addresses.json
Arbie/resources/contracts/balancer/BFactory.json
Arbie/resources/contracts/balancer/BPool.json
Arbie/resources/contracts/balancer/__init__.py
Arbie/resources/contracts/tokens/BadERC20.json
Arbie/resources/contracts/tokens/ERC20.json
Arbie/resources/contracts/tokens/IERC20.json
Arbie/resources/contracts/tokens/MaliciousToken.json
Arbie/resources/contracts/tokens/Weth.json
Arbie/resources/contracts/tokens/__init__.py
Arbie/resources/contracts/uniswap/UniswapV2Factory.json
Arbie/resources/contracts/uniswap/UniswapV2Pair.json
Arbie/resources/contracts/uniswap/UniswapV2Router02.json
Arbie/resources/contracts/uniswap/__init__.py
tests/system/__init__.py
tests/system/app_test.py
tests/system/conftest.py
tests/system/Actions/__init__.py
tests/system/Actions/action_tree_test.py
tests/system/Actions/conftest.py
tests/system/Actions/redis_state_test.py
tests/system/Actions/trader_test.py
tests/system/Contracts/__init__.py
tests/system/Contracts/balancer_test.py
Arbie-0.10.2.dist-info/LICENSE
Arbie-0.10.2.dist-info/METADATA
Arbie-0.10.2.dist-info/WHEEL
Arbie-0.10.2.dist-info/entry_points.txt
Arbie-0.10.2.dist-info/top_level.txt
Arbie-0.10.2.dist-info/RECORD
