Metadata-Version: 2.1
Name: Arbie
Version: 0.10.2
Summary: UNKNOWN
Home-page: UNKNOWN
Author: Alexander Poole
Author-email: alex.o.poole@gmail.com
License: MIT
Platform: UNKNOWN
License-File: LICENSE
Requires-Dist: wheel
Requires-Dist: web3
Requires-Dist: sympy
Requires-Dist: networkx
Requires-Dist: pyyaml
Requires-Dist: docopt
Requires-Dist: redis
Requires-Dist: hiredis
Requires-Dist: prometheus-client
Requires-Dist: prometheus-async
Requires-Dist: requests
